Metadata-Version: 2.1
Name: easy-gaming
Version: 3.0.0
Summary: A gaming automation library
Home-page: 
Author: Luke Cheney
Author-email: thestarfinder8@gmail.com
License: MIT
Keywords: gaming
Classifier: Development Status :: 5 - Production/Stable
Classifier: Intended Audience :: Education
Classifier: Operating System :: Microsoft :: Windows :: Windows 10
Classifier: License :: OSI Approved :: MIT License
Classifier: Programming Language :: Python :: 3
License-File: LICENCE.txt
